batch_prediction_pipeline/__init__.py
batch_prediction_pipeline/batch.py
batch_prediction_pipeline/data.py
batch_prediction_pipeline/monitoring.py
batch_prediction_pipeline/settings.py
batch_prediction_pipeline/utils.py
g_batch_prediction_pipeline-0.3.0.dist-info/METADATA
g_batch_prediction_pipeline-0.3.0.dist-info/WHEEL
g_batch_prediction_pipeline-0.3.0.dist-info/RECORD
