Metadata-Version: 2.1
Name: g-batch-prediction-pipeline
Version: 0.3.0
Summary: 
Author: Iusztin Paul
Author-email: p.e.iusztin@gmail.com
Requires-Python: >=3.9,<3.10
Classifier: Programming Language :: Python :: 3
Classifier: Programming Language :: Python :: 3.9
Requires-Dist: category-encoders (>=2.6.0,<3.0.0)
Requires-Dist: fire (>=0.5.0,<0.6.0)
Requires-Dist: g-training-pipeline (>=0.3.0,<0.4.0)
Requires-Dist: google-cloud-storage (>=2.7.0,<3.0.0)
Requires-Dist: hopsworks (>=3.0.5,<4.0.0)
Requires-Dist: lightgbm (>=3.3.5,<4.0.0)
Requires-Dist: python-dotenv (>=1.0.0,<2.0.0)
Requires-Dist: sktime (>=0.16.1,<0.17.0)
